pydnsviz/__init__.py
pydnsviz/main.py
pydnsviz/core/__init__.py
pydnsviz/core/argparseactions.py
pydnsviz/core/mapper.py
pydnsviz/core/options.py
pydnsviz-0.1.0.dist-info/DESCRIPTION.rst
pydnsviz-0.1.0.dist-info/METADATA
pydnsviz-0.1.0.dist-info/RECORD
pydnsviz-0.1.0.dist-info/WHEEL
pydnsviz-0.1.0.dist-info/entry_points.txt
pydnsviz-0.1.0.dist-info/metadata.json
pydnsviz-0.1.0.dist-info/top_level.txt
