Metadata-Version: 2.0
Name: pydnsviz
Version: 0.1.0
Summary: CLI tool to visualize DNS zones
Home-page: https://github.com/robin-thoni/pydnsviz
Author: Robin Thoni
Author-email: robin@rthoni.com
License: MIT
Keywords: dns graphviz dot
Platform: UNKNOWN
Classifier: Development Status :: 4 - Beta
Classifier: Intended Audience :: System Administrators
Classifier: Topic :: Security
Classifier: Topic :: System :: Installation/Setup
Classifier: Topic :: System :: Networking
Classifier: Topic :: System :: Systems Administration
Classifier: Topic :: Utilities
Classifier: License :: OSI Approved :: MIT License
Classifier: Programming Language :: Python :: 3
Classifier: Programming Language :: Python :: 3.3
Classifier: Programming Language :: Python :: 3.4
Classifier: Programming Language :: Python :: 3.5
Provides-Extra: dev
Provides-Extra: test
Requires-Dist: argparse
Requires-Dist: graphviz
Requires-Dist: dnspython
Provides-Extra: dev
Provides-Extra: test
